duckcp/__init__.py
duckcp/boot/__init__.py
duckcp/boot/meta_command.py
duckcp/boot/repository_command.py
duckcp/boot/storage_command.py
duckcp/boot/task_command.py
duckcp/boot/transformer_command.py
duckcp/configuration/__init__.py
duckcp/configuration/logging_configuration.py
duckcp/configuration/meta_configuration.py
duckcp/constant/__init__.py
duckcp/entity/__init__.py
duckcp/entity/connection.py
duckcp/entity/credential.py
duckcp/entity/executor.py
duckcp/entity/repository.py
duckcp/entity/snapshot.py
duckcp/entity/statement.py
duckcp/entity/storage.py
duckcp/entity/task.py
duckcp/entity/task_transformer.py
duckcp/entity/transform_context.py
duckcp/entity/transformer.py
duckcp/feishu/__init__.py
duckcp/feishu/bitable.py
duckcp/helper/__init__.py
duckcp/helper/click.py
duckcp/helper/collection.py
duckcp/helper/digest.py
duckcp/helper/fs.py
duckcp/helper/http.py
duckcp/helper/serialization.py
duckcp/helper/sql.py
duckcp/helper/validation.py
duckcp/migration/001-repositories.sql
duckcp/migration/002-storages.sql
duckcp/migration/003-transformers.sql
duckcp/migration/004-credentials.sql
duckcp/migration/005-snapshots.sql
duckcp/migration/006-tasks.sql
duckcp/migration/007-tasks-transformers.sql
duckcp/migration/__init__.py
duckcp/projection/__init__.py
duckcp/projection/repository_projection.py
duckcp/projection/storage_projection.py
duckcp/projection/task_projection.py
duckcp/projection/task_transformer_projection.py
duckcp/projection/transformer_projection.py
duckcp/repository/__init__.py
duckcp/repository/bitable_repository.py
duckcp/repository/duckdb_repository.py
duckcp/repository/file_repository.py
duckcp/repository/odps_repository.py
duckcp/repository/postgres_repository.py
duckcp/repository/sqlite_repository.py
duckcp/service/__init__.py
duckcp/service/authentication_service.py
duckcp/service/meta_service.py
duckcp/service/repository_service.py
duckcp/service/snapshot_service.py
duckcp/service/storage_service.py
duckcp/service/task_service.py
duckcp-0.1.3.dist-info/WHEEL
duckcp-0.1.3.dist-info/entry_points.txt
duckcp-0.1.3.dist-info/METADATA
duckcp-0.1.3.dist-info/RECORD
