Metadata-Version: 2.3
Name: duckcp
Version: 0.1.3
Summary: 数据同步工具
Requires-Dist: click>=8.2.1
Requires-Dist: duckdb>=1.3.2
Requires-Dist: pandas>=2.3.1
Requires-Dist: psycopg2-binary>=2.9.10
Requires-Dist: pyodps>=0.12.4
Requires-Dist: rich>=14.1.0
Requires-Dist: sqlglot>=27.4.1
Requires-Python: >=3.12
